pyhdf/HC.py
pyhdf/HDF.py
pyhdf/Makefile
pyhdf/SD.py
pyhdf/V.py
pyhdf/VS.py
pyhdf/__init__.py
pyhdf/_hdfext.cp313-win_amd64.pyd
pyhdf/error.py
pyhdf/hdfext.i
pyhdf/hdfext.py
pyhdf/hdfext_wrap.c
pyhdf/six.py
pyhdf/test_SD.py
pyhdf-0.11.6.dist-info/AUTHORS
pyhdf-0.11.6.dist-info/LICENSE
pyhdf-0.11.6.dist-info/METADATA
pyhdf-0.11.6.dist-info/WHEEL
pyhdf-0.11.6.dist-info/top_level.txt
pyhdf-0.11.6.dist-info/RECORD
