Metadata-Version: 2.1
Name: pyhdf
Version: 0.11.6
Summary: Python interface to the NCSA HDF4 library
Author-email: Andre Gosselin <Andre.Gosselin@dfo-mpo.gc.ca>, "Travis E. Oliphant" <teoliphant@gmail.com>
Maintainer-email: Fazlul Shahriar <fshahriar@gmail.com>
License: MIT License
Project-URL: Homepage, https://github.com/fhs/pyhdf
Keywords: hdf4,netcdf,numpy,python,pyhdf
Classifier: Development Status :: 5 - Production/Stable
Classifier: Intended Audience :: Science/Research
Classifier: Intended Audience :: Developers
Classifier: License :: OSI Approved
Classifier: Programming Language :: C
Classifier: Programming Language :: Python
Classifier: Programming Language :: Python :: 3
Classifier: Topic :: Software Development
Classifier: Topic :: Scientific/Engineering
Classifier: Operating System :: Microsoft :: Windows
Classifier: Operating System :: POSIX
Classifier: Operating System :: Unix
Classifier: Operating System :: MacOS
License-File: LICENSE
License-File: AUTHORS
Requires-Dist: numpy
